[
  {
    "id": "1G2dmOHkECVmXWRfVafA",
    "data": {
      "body": "Ok pronto te aviso \nYa me están confirmando",
      "isFromMe": false,
      "messageId": "23FC22E7A17E31DA6215D4F1C33595C5",
      "from": "5214491518200@c.us",
      "to": "me (MIHuIIg0nPddWQcoEgrsqABLEfw1)",
      "origin": "contact",
      "timestamp": "2025-07-20T23:12:43.991Z"
    },
    "path": "users/MIHuIIg0nPddWQcoEgrsqABLEfw1/chats/5214491518200@c.us/messages_all"
  },
  {
    "id": "2OYJbqcoqeFseV5TAfL8",
    "data": {
      "body": "🙏🏽🙏🏽🙏🏽",
      "isFromMe": false,
      "messageId": "79A0A7A2C5E8ECACE586C9B4879AD6F2",
      "from": "5214491518200@c.us",
      "to": "me (MIHuIIg0nPddWQcoEgrsqABLEfw1)",
      "origin": "contact",
      "timestamp": "2025-07-20T23:12:40.394Z"
    },
    "path": "users/MIHuIIg0nPddWQcoEgrsqABLEfw1/chats/5214491518200@c.us/messages_all"
  },
  {
    "id": "AU53UPqCxeplOyhiF9oc",
    "data": {
      "body": "Hola Nidia buenas tardes",
      "isFromMe": false,
      "messageId": "8DE624C78AC1222254EF2E7F094D5FA0",
      "from": "5214491518200@c.us",
      "to": "me (MIHuIIg0nPddWQcoEgrsqABLEfw1)",
      "origin": "contact",
      "timestamp": "2025-07-20T23:03:15.715Z"
    },
    "path": "users/MIHuIIg0nPddWQcoEgrsqABLEfw1/chats/5214491518200@c.us/messages_all"
  },
  {
    "id": "AcU69wgzDvUTh5F3w7PU",
    "data": {
      "body": "Muy amable",
      "isFromMe": false,
      "messageId": "ED5B3699E9F991E85F4FDE9ADB53B857",
      "from": "5214491518200@c.us",
      "to": "me (MIHuIIg0nPddWQcoEgrsqABLEfw1)",
      "origin": "contact",
      "timestamp": "2025-07-20T23:12:30.890Z"
    },
    "path": "users/MIHuIIg0nPddWQcoEgrsqABLEfw1/chats/5214491518200@c.us/messages_all"
  },
  {
    "id": "AdEo7o3x2OXT7gbnKV3H",
    "data": {
      "body": "Buenas tardes",
      "isFromMe": false,
      "messageId": "AB84BD30C644AC707106DECCEB3D6E91",
      "from": "5214491518200@c.us",
      "to": "me (MIHuIIg0nPddWQcoEgrsqABLEfw1)",
      "origin": "contact",
      "timestamp": "2025-07-18T22:15:56.072Z"
    },
    "path": "users/MIHuIIg0nPddWQcoEgrsqABLEfw1/chats/5214491518200@c.us/messages_all"
  },
  {
    "id": "HN6tmUO0oYYPg6S8V0v7",
    "data": {
      "from": "me (MIHuIIg0nPddWQcoEgrsqABLEfw1)",
      "to": "5214491518200@c.us",
      "body": "Los que deseen asistir, los recibimos con mucho gusto 🙌🏻🌿",
      "isFromMe": true,
      "isAutoReply": false,
      "origin": "human",
      "messageId": "2B5750D5409EA339320EEA64CA9FBCE1",
      "timestamp": "2025-07-20T23:07:41.222Z"
    },
    "path": "users/MIHuIIg0nPddWQcoEgrsqABLEfw1/chats/5214491518200@c.us/messages_all"
  },
  {
    "id": "HqSRWtChSdzFTZjg72P9",
    "data": {
      "from": "me (MIHuIIg0nPddWQcoEgrsqABLEfw1)",
      "to": "5214491518200@c.us",
      "body": "",
      "isFromMe": true,
      "isAutoReply": false,
      "origin": "human",
      "messageId": "DF0655D7B2953DE9DF958B8C72472EE9",
      "timestamp": "2025-07-18T22:33:28.734Z"
    },
    "path": "users/MIHuIIg0nPddWQcoEgrsqABLEfw1/chats/5214491518200@c.us/messages_all"
  },
  {
    "id": "LQPBJ94hBrCycT0NAXGw",
    "data": {
      "body": "Y yo a tus órdenes en Toluca",
      "isFromMe": false,
      "messageId": "7A78A1C5DD7E17521B430B0F70E7ED51",
      "from": "5214491518200@c.us",
      "to": "me (MIHuIIg0nPddWQcoEgrsqABLEfw1)",
      "origin": "contact",
      "timestamp": "2025-07-20T23:12:52.190Z"
    },
    "path": "users/MIHuIIg0nPddWQcoEgrsqABLEfw1/chats/5214491518200@c.us/messages_all"
  },
  {
    "id": "NlqlJS3e3UX6fgIkLaiI",
    "data": {
      "from": "me (MIHuIIg0nPddWQcoEgrsqABLEfw1)",
      "to": "5214491518200@c.us",
      "body": "Hola Mike, buenas tardes!\nigualmente, deseo que estés tendiendo una linda tarde",
      "isFromMe": true,
      "isAutoReply": false,
      "origin": "human",
      "messageId": "EA6029BE9AA04A5E01503311BC0184FE",
      "timestamp": "2025-07-20T23:06:54.424Z"
    },
    "path": "users/MIHuIIg0nPddWQcoEgrsqABLEfw1/chats/5214491518200@c.us/messages_all"
  },
  {
    "id": "QPlygrj2ehVFANR4IF0K",
    "data": {
      "body": "Muy amable",
      "isFromMe": false,
      "messageId": "DCF1C5FA9768994069206117A5B1AC9A",
      "from": "5214491518200@c.us",
      "to": "me (MIHuIIg0nPddWQcoEgrsqABLEfw1)",
      "origin": "contact",
      "timestamp": "2025-07-20T05:09:17.386Z"
    },
    "path": "users/MIHuIIg0nPddWQcoEgrsqABLEfw1/chats/5214491518200@c.us/messages_all"
  },
  {
    "id": "RWsDnFKidfMUKhqO16aM",
    "data": {
      "body": "Ntp mil gracias",
      "isFromMe": false,
      "messageId": "AEE0C8214685E13040804A20821FEE45",
      "from": "5214491518200@c.us",
      "to": "me (MIHuIIg0nPddWQcoEgrsqABLEfw1)",
      "origin": "contact",
      "timestamp": "2025-07-20T05:09:07.883Z"
    },
    "path": "users/MIHuIIg0nPddWQcoEgrsqABLEfw1/chats/5214491518200@c.us/messages_all"
  },
  {
    "id": "RyqGJ2b5ayGqjabxA5iB",
    "data": {
      "body": "",
      "isFromMe": false,
      "messageId": "FCE137DFD7A262F71038573A78AD1967",
      "from": "5214491518200@c.us",
      "to": "me (MIHuIIg0nPddWQcoEgrsqABLEfw1)",
      "origin": "contact",
      "timestamp": "2025-07-18T22:16:32.527Z"
    },
    "path": "users/MIHuIIg0nPddWQcoEgrsqABLEfw1/chats/5214491518200@c.us/messages_all"
  },
  {
    "id": "VqkEl7iklWyEuCap8uGH",
    "data": {
      "body": "Muchísimas gracias",
      "isFromMe": false,
      "messageId": "C974A05AE726427299143CEB5A0AF1D7",
      "from": "5214491518200@c.us",
      "to": "me (MIHuIIg0nPddWQcoEgrsqABLEfw1)",
      "origin": "contact",
      "timestamp": "2025-07-20T23:12:22.491Z"
    },
    "path": "users/MIHuIIg0nPddWQcoEgrsqABLEfw1/chats/5214491518200@c.us/messages_all"
  },
  {
    "id": "X9pdwDD4JB1xNTwQBeV8",
    "data": {
      "body": "Mil mil gracias\nNidia \n\nFuerte abrazo y bendiciones",
      "isFromMe": false,
      "messageId": "9CCC71E6D4F58FADAFE300307FAC8415",
      "from": "5214491518200@c.us",
      "to": "me (MIHuIIg0nPddWQcoEgrsqABLEfw1)",
      "origin": "contact",
      "timestamp": "2025-07-21T00:10:58.899Z"
    },
    "path": "users/MIHuIIg0nPddWQcoEgrsqABLEfw1/chats/5214491518200@c.us/messages_all"
  },
  {
    "id": "Yx7BRX7DgHLMiIvncQHy",
    "data": {
      "body": "Hola Nidia",
      "isFromMe": false,
      "messageId": "C76B0326C4CA7CB6CE556E452675CFAD",
      "from": "5214491518200@c.us",
      "to": "me (MIHuIIg0nPddWQcoEgrsqABLEfw1)",
      "origin": "contact",
      "timestamp": "2025-07-18T22:15:53.772Z"
    },
    "path": "users/MIHuIIg0nPddWQcoEgrsqABLEfw1/chats/5214491518200@c.us/messages_all"
  },
  {
    "id": "Z3Dcm3QIPCzdMsWXE8kD",
    "data": {
      "body": "Mil gracias",
      "isFromMe": false,
      "messageId": "2B7980DC424E285516D7852E10507308",
      "from": "5214491518200@c.us",
      "to": "me (MIHuIIg0nPddWQcoEgrsqABLEfw1)",
      "origin": "contact",
      "timestamp": "2025-07-20T23:04:00.425Z"
    },
    "path": "users/MIHuIIg0nPddWQcoEgrsqABLEfw1/chats/5214491518200@c.us/messages_all"
  },
  {
    "id": "cGR5BdEo07jbLYs6Dfq2",
    "data": {
      "from": "me (MIHuIIg0nPddWQcoEgrsqABLEfw1)",
      "to": "5214491518200@c.us",
      "body": "",
      "isFromMe": true,
      "isAutoReply": false,
      "origin": "human",
      "messageId": "E474E861076C9A89CE416A70BCCA1AA8",
      "timestamp": "2025-07-20T23:17:50.118Z"
    },
    "path": "users/MIHuIIg0nPddWQcoEgrsqABLEfw1/chats/5214491518200@c.us/messages_all"
  },
  {
    "id": "fAXMSN0ql07mX6kXZL0B",
    "data": {
      "from": "me (MIHuIIg0nPddWQcoEgrsqABLEfw1)",
      "to": "5214491518200@c.us",
      "body": "Bendiciones Mike 🙌🏻🫂 que tengas linda tarde",
      "isFromMe": true,
      "isAutoReply": false,
      "origin": "human",
      "messageId": "BD2B51A084F2D7BE1BCA70886116A607",
      "timestamp": "2025-07-21T00:21:47.318Z"
    },
    "path": "users/MIHuIIg0nPddWQcoEgrsqABLEfw1/chats/5214491518200@c.us/messages_all"
  },
  {
    "id": "l1TZ2jdhPGbJkQFnplaY",
    "data": {
      "body": "",
      "isFromMe": false,
      "messageId": "423B5C988A3CCD0478D5E11D9D6C39E0",
      "from": "5214491518200@c.us",
      "to": "me (MIHuIIg0nPddWQcoEgrsqABLEfw1)",
      "origin": "contact",
      "timestamp": "2025-07-18T22:36:44.653Z"
    },
    "path": "users/MIHuIIg0nPddWQcoEgrsqABLEfw1/chats/5214491518200@c.us/messages_all"
  },
  {
    "id": "nAMorNXxyjyYeIrNvmEI",
    "data": {
      "body": "Deseo estés super bien",
      "isFromMe": false,
      "messageId": "C587F7E1A70BB064D5040DC3C47EC692",
      "from": "5214491518200@c.us",
      "to": "me (MIHuIIg0nPddWQcoEgrsqABLEfw1)",
      "origin": "contact",
      "timestamp": "2025-07-20T23:03:24.090Z"
    },
    "path": "users/MIHuIIg0nPddWQcoEgrsqABLEfw1/chats/5214491518200@c.us/messages_all"
  },
  {
    "id": "oPy5acKl7B3ftYz6JoH0",
    "data": {
      "from": "me (MIHuIIg0nPddWQcoEgrsqABLEfw1)",
      "to": "5214491518200@c.us",
      "body": "Al contrario, gracias a ti Mike! Descansa 😁",
      "isFromMe": true,
      "isAutoReply": false,
      "origin": "human",
      "messageId": "7DC7242EACFD7BD6C1460FB5B9611C47",
      "timestamp": "2025-07-20T05:15:51.721Z"
    },
    "path": "users/MIHuIIg0nPddWQcoEgrsqABLEfw1/chats/5214491518200@c.us/messages_all"
  },
  {
    "id": "sgN2pbSn2FxxcV9oIQed",
    "data": {
      "from": "me (MIHuIIg0nPddWQcoEgrsqABLEfw1)",
      "to": "5214491518200@c.us",
      "body": "",
      "isFromMe": true,
      "isAutoReply": false,
      "origin": "human",
      "messageId": "E36395A43F20FCB91D8546F4344A4EAC",
      "timestamp": "2025-07-20T02:21:14.690Z"
    },
    "path": "users/MIHuIIg0nPddWQcoEgrsqABLEfw1/chats/5214491518200@c.us/messages_all"
  },
  {
    "id": "ujehf0UJMfksM1mAmMuB",
    "data": {
      "body": "Por favor\nPara preguntarte cuántos líderes puedo mandarte para el martes \nOlvide preguntarte eso ?",
      "isFromMe": false,
      "messageId": "8D197CE461C052FF6D7B330A9648AF37",
      "from": "5214491518200@c.us",
      "to": "me (MIHuIIg0nPddWQcoEgrsqABLEfw1)",
      "origin": "contact",
      "timestamp": "2025-07-20T23:03:54.588Z"
    },
    "path": "users/MIHuIIg0nPddWQcoEgrsqABLEfw1/chats/5214491518200@c.us/messages_all"
  },
  {
    "id": "xizqSPw6lS7hTL5wJOop",
    "data": {
      "body": "Fuerte abrazo y bendiciones",
      "isFromMe": false,
      "messageId": "0C9CDCFC697021F7D191DD38356F1B63",
      "from": "5214491518200@c.us",
      "to": "me (MIHuIIg0nPddWQcoEgrsqABLEfw1)",
      "origin": "contact",
      "timestamp": "2025-07-20T23:12:50.291Z"
    },
    "path": "users/MIHuIIg0nPddWQcoEgrsqABLEfw1/chats/5214491518200@c.us/messages_all"
  }
]